MANIFEST.in
setup.py
Products/__init__.py
Products.SilvaViews.egg-info/PKG-INFO
Products.SilvaViews.egg-info/SOURCES.txt
Products.SilvaViews.egg-info/dependency_links.txt
Products.SilvaViews.egg-info/namespace_packages.txt
Products.SilvaViews.egg-info/not-zip-safe
Products.SilvaViews.egg-info/requires.txt
Products.SilvaViews.egg-info/top_level.txt
Products/SilvaViews/CREDITS.txt
Products/SilvaViews/HISTORY.txt
Products/SilvaViews/INSTALL.txt
Products/SilvaViews/LICENSE.txt
Products/SilvaViews/MultiViewRegistry.py
Products/SilvaViews/README.txt
Products/SilvaViews/ViewRegistry.py
Products/SilvaViews/__init__.py
Products/SilvaViews/helpers.py
Products/SilvaViews/interfaces.py
Products/SilvaViews/version.txt
Products/SilvaViews/www/multiViewRegistryAdd.zpt
Products/SilvaViews/www/silva_multi_view_registry.gif
Products/SilvaViews/www/silva_view_registry.gif
Products/SilvaViews/www/viewRegistryAdd.zpt
Products/SilvaViews/www/viewRegistryAssociations.zpt