Metadata-Version: 1.1
Name: Products.SilvaViews
Version: 0.16.2
Summary: Zope 2 views machinery for Silva 2
Home-page: http://infrae.com/products/silva
Author: Infrae
Author-email: info@infrae.com
License: BSD
Keywords: silva views zope2
Platform: UNKNOWN
Classifier: Framework :: Zope2
Classifier: License :: OSI Approved :: BSD License
Classifier: Programming Language :: Python
Classifier: Topic :: Software Development :: Libraries :: Python Modules
